<?xml version="1.0"?>
<opencv_storage>
<stage8>
  <maxWeakCount>8</maxWeakCount>
  <stageThreshold>-8.7115681171417236e-01</stageThreshold>
  <weakClassifiers>
    <_>
      <internalNodes>
        0 -1 19260 199173247 185057302 -2125438761 4113 1116541523
        -2135946488 -2004058111 -89487088</internalNodes>
      <leafValues>
        -5.9047621488571167e-01 5.4915255308151245e-01</leafValues></_>
    <_>
      <internalNodes>
        0 -1 15702 -10172417 -742004827 2143271467 -772171932 -264986433
        -1391364996 -868374277 -71992873</internalNodes>
      <leafValues>
        -3.4008297324180603e-01 7.1778273582458496e-01</leafValues></_>
    <_>
      <internalNodes>
        0 -1 23978 -2013817601 -1561133059 -57353 2126445159 -1124253874
        -1346928641 1786707199 -1431636809</internalNodes>
      <leafValues>
        -4.4671612977981567e-01 5.5625176429748535e-01</leafValues></_>
    <_>
      <internalNodes>
        0 -1 13642 -1367867393 677883375 -16779721 1928591991 213870387
        -1895891084 -839394057 -867080399</internalNodes>
      <leafValues>
        -4.4022500514984131e-01 5.2607882022857666e-01</leafValues></_>
    <_>
      <internalNodes>
        0 -1 16724 1461818739 -1727856413 143321219 1451229315
        -1991929606 -1810825214 -327087479 136119698</internalNodes>
      <leafValues>
        -6.4007133245468140e-01 3.6493217945098877e-01</leafValues></_>
    <_>
      <internalNodes>
        0 -1 18798 1539434733 1971392528 233491 -175782783 -108998519
        1216413706 1208713878 -1798991584</internalNodes>
      <leafValues>
        -5.1189970970153809e-01 5.0408971309661865e-01</leafValues></_>
    <_>
      <internalNodes>
        0 -1 12144 1436658294 -251657465 -2012142252 383295555
        -2012569458 -1699992957 -1727881055 -1494744693</internalNodes>
      <leafValues>
        -4.9302387237548828e-01 5.2012336254119873e-01</leafValues></_>
    <_>
      <internalNodes>
        0 -1 10982 -759699117 -637643205 2063597245 1543437787
        -856276848 2137445879 -1921572912 -1090584759</internalNodes>
      <leafValues>
        -3.9121985435485840e-01 6.2206661701202393e-01</leafValues></_></weakClassifiers></stage8>
</opencv_storage>
