<?xml version="1.0"?>
<opencv_storage>
<stage12>
  <maxWeakCount>7</maxWeakCount>
  <stageThreshold>-1.0882210731506348e+00</stageThreshold>
  <weakClassifiers>
    <_>
      <internalNodes>
        0 -1 14951 1431377405 1059184051 -554304257 1026678199
        1490146815 -537343557 368795391 -8650753</internalNodes>
      <leafValues>
        -5.0400000810623169e-01 6.7811763286590576e-01</leafValues></_>
    <_>
      <internalNodes>
        0 -1 11443 -586434625 -46986504 -832440122 2100546202 1160497342
        -880080672 -2010472785 250257810</internalNodes>
      <leafValues>
        -5.5361008644104004e-01 5.5960613489151001e-01</leafValues></_>
    <_>
      <internalNodes>
        0 -1 18738 -511508085 -238477277 16780485 2068441227 307854
        193012106 33851035 1133413546</internalNodes>
      <leafValues>
        -7.1419399976730347e-01 4.2357942461967468e-01</leafValues></_>
    <_>
      <internalNodes>
        0 -1 18081 1755116739 -628585830 -1065025023 -562000608
        -938293093 -561346559 -851264637 -389848792</internalNodes>
      <leafValues>
        -6.4030915498733521e-01 4.7002509236335754e-01</leafValues></_>
    <_>
      <internalNodes>
        0 -1 21626 -1307067542 -682802907 -1756154832 487658246
        1375832857 1132757251 -2128082456 -1143502950</internalNodes>
      <leafValues>
        -6.4390838146209717e-01 4.6193721890449524e-01</leafValues></_>
    <_>
      <internalNodes>
        0 -1 17061 -615663631 1060181845 -665708585 869075227 285279863
        288620593 1155581619 535776553</internalNodes>
      <leafValues>
        -7.4053865671157837e-01 4.1711336374282837e-01</leafValues></_>
    <_>
      <internalNodes>
        0 -1 12542 -545153149 -90504869 -1069259822 -231694389
        -108523510 -358068094 -909573806 -1615331319</internalNodes>
      <leafValues>
        -6.2105685472488403e-01 4.7878021001815796e-01</leafValues></_></weakClassifiers></stage12>
</opencv_storage>
